{
    "name":"Supplementaries",
    "icon":"supplementaries:globe",
    "category":"smalltips",
    "pages":[
        {
            "type":"text",
            "text":"Supplementaries是一个装饰和实用类模组，加入了一些既美观又实用的物品。$(br)    在JEI搜索栏输入 @supplementaries 查看此模组的所有物品。"
        },
        {
            "type":"crafting",
            "recipe":"supplementaries:hanging_signs/hanging_sign_oak",
            "text":"任何木头都可以制作这种招牌，可以用物品右键设置图标或者空手右键设置文本。"
        },
        {
            "type":"crafting",
            "recipe":"supplementaries:sign_posts/sign_post_oak",
            "text":"任何木头都可以制作这种路标，可以放在栅栏侧面，用绑定了磁石的指南针指定方向。"
        },
        {
            "type":"crafting",
            "recipe":"minecraft:lantern",
            "text":"灯笼可以挂在墙上和栅栏上，也支持Skinned Lanterns的灯笼。"
        },
        {
            "type":"crafting",
            "recipe":"supplementaries:planter",
            "text":"无需浇水就可以种植作物。"
        },
        {
            "type":"crafting",
            "recipe":"supplementaries:pedestal",
            "text":"用来展示物品，也可以当柱子用。"
        },
        {
            "type":"crafting",
            "recipe":"supplementaries:notice_board",
            "text":"可以放入地图、书和旗帜图案。"
        },
        {
            "type":"spotlight",
            "item":"supplementaries:safe",
            "text":"需要搭配本模组的钥匙使用，只有同名的钥匙才能打开同名的保险箱。"
        },
        {
            "type":"crafting",
            "recipe":"supplementaries:cage",
            "text":"右键抓捕小型生物。"
        },
        {
            "type":"crafting",
            "recipe":"supplementaries:crank",
            "text":"精确输出红石信号。SHIFT+右键改变旋转方向。"
        },
        {
            "type":"crafting",
            "recipe":"supplementaries:turn_table",
            "text":"输入红石信号时旋转对应面的方块/实体，速度由信号强度决定。"
        },
        {
            "type":"crafting",
            "recipe":"supplementaries:hourglass",
            "text":"可放入各种沙子和各种粉末，不同粉末的计时长度不同，用转盘可以旋转沙漏。"
        },
        {
            "type":"spotlight",
            "item":"supplementaries:rope_arrow",
            "text":"射中方块下方时垂下一条绳索。"
        },
        {
            "type":"crafting",
            "recipe":"supplementaries:pulley",
            "text":"放入绳索或者铁链，用曲柄控制放下绳索的方向，触底后反向旋转提起绳索末端接触的方块。"
        },
        {
            "type":"crafting",
            "recipe":"supplementaries:faucet",
            "text":"排出罐/炼药锅里的液体。"
        }
    ]
}